bin/__init__.py
fenci/__init__.py
nlp_fenci-1.2.3.data/scripts/baidu_fenci
nlp_fenci-1.2.3.data/scripts/sougou_fenci
nlp_fenci-1.2.3.dist-info/METADATA
nlp_fenci-1.2.3.dist-info/WHEEL
nlp_fenci-1.2.3.dist-info/top_level.txt
nlp_fenci-1.2.3.dist-info/RECORD
