Metadata-Version: 2.1
Name: nlp-fenci
Version: 1.2.3
Summary: 分词工具
Home-page: https://github.com/SharpCX/sougou_fenci.git
Author: cx
Author-email: sharpcx@live.com
License: UNKNOWN
Platform: UNKNOWN
Classifier: Programming Language :: Python :: 3
Classifier: License :: OSI Approved :: MIT License
Classifier: Operating System :: OS Independent
Requires-Dist: requests
